{
  "degrees": [
    {
      "title": "Master of Computer Application",
      "university": "Guru Gobind Singh Indraprastha University",
      "date": "2024 — Present",
      "description": "Advanced study of Software Engineering, Distributed Systems, Database Management, and Machine Learning"
    },
    {
      "title": "Bachelor of Science in Computer Science",
      "university": "University of Delhi",
      "date": "2021 — 2024",
      "description": "Obtained a solid foundation in computer science principles — Data Structures, Algorithms, Object-Oriented Programming, and System Design."
    }
  ]
}
